_navitools.cpython-39-i386-linux-gnu.so
navitools-0.0.2.dist-info/RECORD
navitools-0.0.2.dist-info/WHEEL
navitools-0.0.2.dist-info/METADATA
navitools-0.0.2.dist-info/top_level.txt
navitools-0.0.2.dist-info/LICENSE
navitools/__init__.py
navitools/testing/common.py
navitools/testing/__init__.py
